mcp_server_email_cuhksz/__init__.py
mcp_server_email_cuhksz/__main__.py
mcp_server_email_cuhksz/email.json
mcp_server_email_cuhksz/mcp_email.py
mcp_server_email_cuhksz-0.1.4.dist-info/licenses/LICENSE
mcp_server_email_cuhksz-0.1.4.dist-info/METADATA
mcp_server_email_cuhksz-0.1.4.dist-info/WHEEL
mcp_server_email_cuhksz-0.1.4.dist-info/entry_points.txt
mcp_server_email_cuhksz-0.1.4.dist-info/top_level.txt
mcp_server_email_cuhksz-0.1.4.dist-info/RECORD
