Metadata-Version: 2.4
Name: mcp-server-email-cuhksz
Version: 0.1.4
Summary: A Model Context Protocol server for email
Author-email: LKCY23 <lkcydream@gmail.com>
License: MIT
Keywords: CUHKSZ,MCP,Email
Classifier: Programming Language :: Python :: 3
Classifier: License :: OSI Approved :: MIT License
Classifier: Operating System :: OS Independent
Requires-Python: >=3.9
License-File: LICENSE
Requires-Dist: mcp>=1.12.0
Requires-Dist: fastmcp>=2.0.0
Requires-Dist: python-dotenv
Requires-Dist: pydantic
Dynamic: license-file
